rdflib_rdfcbor/__init__.py
rdflib_rdfcbor/content_addressable.py
rdflib_rdfcbor/dictionary.py
rdflib_rdfcbor/molecule.py
rdflib_rdfcbor/parser.py
rdflib_rdfcbor/serializer.py
rdflib_rdfcbor/term.py
rdflib_rdfcbor-0.1.0.dist-info/METADATA
rdflib_rdfcbor-0.1.0.dist-info/WHEEL
rdflib_rdfcbor-0.1.0.dist-info/licenses/COPYING
rdflib_rdfcbor-0.1.0.dist-info/RECORD
