Metadata-Version: 2.3
Name: rdflib-rdfcbor
Version: 0.1.0
Summary: RDFLib plugin for the RDF/CBOR serialization
Project-URL: Homepage, https://codeberg.org/ctrlall/rdflib-rdfcbor
Project-URL: Bug Tracker, https://codeberg.org/ctrlall/rdflib-rdfcbor/issues
Author-email: pukkamustard <pukkamustard@posteo.net>, Moritz Feichtinger <moritz.feichtinger@unibas.ch>
License: GNU AFFERO GENERAL PUBLIC LICENSE
License-File: COPYING
Classifier: License :: OSI Approved :: GNU Affero General Public License v3 or later (AGPLv3+)
Classifier: Operating System :: OS Independent
Classifier: Programming Language :: Python :: 3
Requires-Python: >=3.10
Requires-Dist: cbor2
Requires-Dist: rdflib
